esapythonsdk/__init__.py
esapythonsdk-0.0.29.dist-info/LICENSE
esapythonsdk-0.0.29.dist-info/METADATA
esapythonsdk-0.0.29.dist-info/WHEEL
esapythonsdk-0.0.29.dist-info/top_level.txt
esapythonsdk-0.0.29.dist-info/RECORD
