Metadata-Version: 2.1
Name: esapythonsdk
Version: 0.0.29
Summary: The ESA SDK for Python.
Author: Michael Cloutier
Author-email: michael.cloutier@experian.com
Requires-Python: >=3.10
License-File: LICENSE
Requires-Dist: requests
